[
{
  "_id": "6068bc028c03d4974cef4960",
  "web_url": "https://www.dailystar.co.uk/news/world-news/unknown-disease-turns-bear-cubs-23829469",
  "postDate": "2021-03-31T00:00:00.000Z",
  "headline": "Unknown disease that turns bear cubs into friendly \"zombies\" spreading rapidly in US",
  "text_body": "A mystery virus infecting young black bears in the US states of California and Nevada makes the animals behave in a strangely friendly manner towards humans.",
  "correct_answer": true,
  "__v": 0
}
]
